llm_ollama/__init__.py
llm_ollama/auth.py
llm_ollama/cache.py
llm_ollama-0.15.0.dist-info/licenses/LICENSE
llm_ollama-0.15.0.dist-info/METADATA
llm_ollama-0.15.0.dist-info/WHEEL
llm_ollama-0.15.0.dist-info/entry_points.txt
llm_ollama-0.15.0.dist-info/top_level.txt
llm_ollama-0.15.0.dist-info/RECORD
