Metadata-Version: 2.4
Name: llm-ollama
Version: 0.15.0
Summary: LLM plugin providing access to models running on an Ollama server
Author: Sergey Alexandrov
License: Apache-2.0
Project-URL: Homepage, https://github.com/taketwo/llm-ollama
Project-URL: Changelog, https://github.com/taketwo/llm-ollama/releases
Project-URL: Issues, https://github.com/taketwo/llm-ollama/issues
Project-URL: CI, https://github.com/taketwo/llm-ollama/actions
Classifier: License :: OSI Approved :: Apache Software License
Requires-Python: >=3.9
License-File: LICENSE
Requires-Dist: llm>=0.26
Requires-Dist: ollama>=0.6.0
Requires-Dist: pydantic>=2
Provides-Extra: test
Requires-Dist: pytest; extra == "test"
Requires-Dist: pytest-asyncio; extra == "test"
Requires-Dist: pytest-mock; extra == "test"
Provides-Extra: lint
Requires-Dist: ruff; extra == "lint"
Dynamic: license-file
